MANIFEST.in
README.md
VERSION
setup.py
BiblioPixelAnimations/__init__.py
BiblioPixelAnimations.egg-info/PKG-INFO
BiblioPixelAnimations.egg-info/SOURCES.txt
BiblioPixelAnimations.egg-info/dependency_links.txt
BiblioPixelAnimations.egg-info/top_level.txt
BiblioPixelAnimations/base/Twinkle.py
BiblioPixelAnimations/base/__init__.py
BiblioPixelAnimations/circle/Twinkle.py
BiblioPixelAnimations/circle/__init__.py
BiblioPixelAnimations/circle/arc_clock.py
BiblioPixelAnimations/circle/arc_rotate.py
BiblioPixelAnimations/circle/bloom.py
BiblioPixelAnimations/circle/circle_clock.py
BiblioPixelAnimations/circle/diag.py
BiblioPixelAnimations/circle/fill.py
BiblioPixelAnimations/circle/fireflies.py
BiblioPixelAnimations/circle/hyperspace.py
BiblioPixelAnimations/circle/pinwheel.py
BiblioPixelAnimations/circle/ring_clock.py
BiblioPixelAnimations/circle/swirl.py
BiblioPixelAnimations/cube/GameOfLife.py
BiblioPixelAnimations/cube/Rain.py
BiblioPixelAnimations/cube/__init__.py
BiblioPixelAnimations/cube/bloom.py
BiblioPixelAnimations/cube/simplex.py
BiblioPixelAnimations/cube/wave_spiral.py
BiblioPixelAnimations/cube/spectrum/__init__.py
BiblioPixelAnimations/cube/spectrum/system_eq.py
BiblioPixelAnimations/game/Snake.py
BiblioPixelAnimations/game/Tetris.py
BiblioPixelAnimations/game/__init__.py
BiblioPixelAnimations/game/flappy.py
BiblioPixelAnimations/matrix/AnalogClock.py
BiblioPixelAnimations/matrix/BinaryClock.py
BiblioPixelAnimations/matrix/CPUUsage.py
BiblioPixelAnimations/matrix/GameOfLife.py
BiblioPixelAnimations/matrix/GradientClock.py
BiblioPixelAnimations/matrix/ImageAnim.py
BiblioPixelAnimations/matrix/ImageDissolve.py
BiblioPixelAnimations/matrix/ImageShow.py
BiblioPixelAnimations/matrix/LangtonsAnt.py
BiblioPixelAnimations/matrix/Mainframe.py
BiblioPixelAnimations/matrix/MathFunc.py
BiblioPixelAnimations/matrix/MatrixRain.py
BiblioPixelAnimations/matrix/OneKClock.py
BiblioPixelAnimations/matrix/ScreenGrab.py
BiblioPixelAnimations/matrix/SpinningTriangle.py
BiblioPixelAnimations/matrix/TallClock.py
BiblioPixelAnimations/matrix/Text.py
BiblioPixelAnimations/matrix/TicTacToe.py
BiblioPixelAnimations/matrix/Twinkle.py
