Metadata-Version: 1.1
Name: BiblioPixelAnimations
Version: 3.20190410.153508
Summary: BiblioPixelAnimations is an animation repository for animation classes that work with BiblioPixel: http://github.com/maniacallabs/BiblioPixel
Home-page: http://github.com/maniacallabs/BiblioPixelAnimations/
Author: Adam Haile
Author-email: adam@maniacallabs.com
License: MIT
Platform: UNKNOWN
Classifier: Development Status :: 5 - Production/Stable
Classifier: License :: OSI Approved :: MIT License
Classifier: Programming Language :: Python :: 3.4
Classifier: Programming Language :: Python :: 3.5
Classifier: Programming Language :: Python :: 3.6
